helmgen/__init__.py
helmgen/__main__.py
helmgen/generator.py
helmgen/helm_templates/deployment.yaml
helmgen/helm_templates/externalsecret.yaml
helmgen/helm_templates/ingress.yaml
helmgen/helm_templates/pvc.yaml
helmgen/helm_templates/secrets.yaml
helmgen/helm_templates/secretstore.yaml
helmgen/helm_templates/service.yaml
helmgen-0.1.0.dist-info/licenses/LICENSE
helmgen-0.1.0.dist-info/METADATA
helmgen-0.1.0.dist-info/WHEEL
helmgen-0.1.0.dist-info/entry_points.txt
helmgen-0.1.0.dist-info/top_level.txt
helmgen-0.1.0.dist-info/RECORD
