Metadata-Version: 2.4
Name: helmgen
Version: 0.1.0
Summary: Auto-generate Helm charts from Docker Compose files
Author-email: Marcelo Garcia <marcelo.garcia@linux.com>
License: MIT
Project-URL: homepage, https://github.com/marcelodevops/helmgen
Project-URL: repository, https://github.com/marcelodevops/helmgen
Project-URL: issues, https://github.com/marcelodevops/helmgen/issues
Requires-Python: >=3.8
License-File: LICENSE
Requires-Dist: PyYAML>=6.0.2
Requires-Dist: ruamel.yaml>=0.18.6
Requires-Dist: jinja2>=3.1.4
Requires-Dist: click>=8.1.7
Requires-Dist: rich>=13.7.1
Dynamic: license-file
